sve/__init__.py
sve/__version__.py
sve/entries.py
sve/output.py
sve/service_info.py
sve/sve.py
sve/utils.py
sve-0.3.2.dist-info/LICENSE
sve-0.3.2.dist-info/METADATA
sve-0.3.2.dist-info/WHEEL
sve-0.3.2.dist-info/entry_points.txt
sve-0.3.2.dist-info/top_level.txt
sve-0.3.2.dist-info/RECORD
