Metadata-Version: 2.1
Name: sve
Version: 0.3.2
Summary: Service vulnerability enumeration tool
Home-page: https://github.com/bl0nd/sve
Author: Jason Phan
Author-email: xorblonded@gmail.com
License: MIT
Platform: UNKNOWN
Classifier: Development Status :: 5 - Production/Stable
Classifier: Intended Audience :: End Users/Desktop
Classifier: Natural Language :: English
Classifier: License :: OSI Approved :: MIT License
Classifier: Programming Language :: Python
Classifier: Programming Language :: Python :: 3.7
Requires-Python: >=3.7
